pushshift_comment_export/__init__.py
pushshift_comment_export/__main__.py
pushshift_comment_export/dal.py
pushshift_comment_export/py.typed
pushshift_comment_export-0.1.4.dist-info/LICENSE
pushshift_comment_export-0.1.4.dist-info/METADATA
pushshift_comment_export-0.1.4.dist-info/WHEEL
pushshift_comment_export-0.1.4.dist-info/entry_points.txt
pushshift_comment_export-0.1.4.dist-info/top_level.txt
pushshift_comment_export-0.1.4.dist-info/RECORD
