Metadata-Version: 2.1
Name: pushshift-comment-export
Version: 0.1.4
Summary: Exports all accessible reddit comments for an account using pushshift
Home-page: https://github.com/seanbreckenridge/pushshift_comment_export
Author: Sean Breckenridge
Author-email: seanbrecke@gmail.com
License: MIT
Keywords: reddit data
Classifier: License :: OSI Approved :: MIT License
Classifier: Programming Language :: Python
Classifier: Programming Language :: Python :: 3
Classifier: Programming Language :: Python :: 3.7
Classifier: Programming Language :: Python :: 3.8
Classifier: Programming Language :: Python :: 3.9
Classifier: Programming Language :: Python :: 3.10
License-File: LICENSE
Requires-Dist: logzero
Requires-Dist: backoff
Requires-Dist: requests
Requires-Dist: click
